{
    "categories":[
        {
            "name":"FP"
        },
        {
            "name":"SFG"
        },
        {
            "name":"IFG"
        },
        {
            "name":"OrG"
        },
        {
            "name":"M1"
        },
        {
            "name":"PM"
        },
        {
            "name":"PoCG"
        },
        {
            "name":"FPO"
        },
        {
            "name":"SPL"
        },
        {
            "name":"IPL"
        },
        {
            "name":"PrCu"
        },
        {
            "name":"PRL"
        },
        {
            "name":"STG"
        },
        {
            "name":"ITG"
        },
        {
            "name":"PHG"
        },
        {
            "name":"TP"
        },
        {
            "name":"V1"
        },
        {
            "name":"V2"
        },
        {
            "name":"VMO"
        },
        {
            "name":"INS"
        },
        {
            "name":"CG"
        },
        {
            "name":"Acb"
        },
        {
            "name":"Amyg"
        },
        {
            "name":"Cd"
        },
        {
            "name":"HF"
        },
        {
            "name":"Hy"
        },
        {
            "name":"GP"
        },
        {
            "name":"Pu"
        },
        {
            "name":"Tha"
        }
    ],
    "nodes":[
        {
            "id":0,
            "name":"FP.d",
            "symbolSize":10,
            "value":3,
            "label":{
                "normal":{
                    "show":true
                }
            },
            "category":0.0
        },
        {
            "id":1,
            "name":"FP.m",
            "symbolSize":10,
            "value":3,
            "label":{
                "normal":{
                    "show":true
                }
            },
            "category":0.0
        },
        {
            "id":2,
            "name":"FP.v",
            "symbolSize":10,
            "value":3,
            "label":{
                "normal":{
                    "show":true
                }
            },
            "category":0.0
        },
        {
            "id":3,
            "name":"SFG.rm",
            "symbolSize":10,
            "value":3,
            "label":{
                "normal":{
                    "show":true
                }
            },
            "category":1.0
        },
        {
            "id":4,
            "name":"SFG.cm",
            "symbolSize":10,
            "value":3,
            "label":{
                "normal":{
                    "show":true
                }
            },
            "category":1.0
        },
        {
            "id":5,
            "name":"SFG.r",
            "symbolSize":10,
            "value":3,
            "label":{
                "normal":{
                    "show":true
                }
            },
            "category":1.0
        },
        {
            "id":6,
            "name":"SFG.ri",
            "symbolSize":10,
            "value":3,
            "label":{
                "normal":{
                    "show":true
                }
            },
            "category":1.0
        },
        {
            "id":7,
            "name":"SFG.ci",
            "symbolSize":10,
            "value":3,
            "label":{
                "normal":{
                    "show":true
                }
            },
            "category":1.0
        },
        {
            "id":8,
            "name":"SFG.c",
            "symbolSize":10,
            "value":3,
            "label":{
                "normal":{
                    "show":true
                }
            },
            "category":1.0
        },
        {
            "id":9,
            "name":"IFG.rd",
            "symbolSize":10,
            "value":3,
            "label":{
                "normal":{
                    "show":true
                }
            },
            "category":2.0
        },
        {
            "id":10,
            "name":"IFG.cd",
            "symbolSize":10,
            "value":3,
            "label":{
                "normal":{
                    "show":true
                }
            },
            "category":2.0
        },
        {
            "id":11,
            "name":"IFG.cv",
            "symbolSize":10,
            "value":3,
            "label":{
                "normal":{
                    "show":true
                }
            },
            "category":2.0
        },
        {
            "id":12,
            "name":"IFG.iv",
            "symbolSize":10,
            "value":3,
            "label":{
                "normal":{
                    "show":true
                }
            },
            "category":2.0
        },
        {
            "id":13,
            "name":"IFG.rv",
            "symbolSize":10,
            "value":3,
            "label":{
                "normal":{
                    "show":true
                }
            },
            "category":2.0
        },
        {
            "id":14,
            "name":"OrG.rm",
            "symbolSize":10,
            "value":3,
            "label":{
                "normal":{
                    "show":true
                }
            },
            "category":3.0
        },
        {
            "id":15,
            "name":"OrG.cm",
            "symbolSize":10,
            "value":3,
            "label":{
                "normal":{
                    "show":true
                }
            },
            "category":3.0
        },
        {
            "id":16,
            "name":"OrG.ri",
            "symbolSize":10,
            "value":3,
            "label":{
                "normal":{
                    "show":true
                }
            },
            "category":3.0
        },
        {
            "id":17,
            "name":"OrG.ci",
            "symbolSize":10,
            "value":3,
            "label":{
                "normal":{
                    "show":true
                }
            },
            "category":3.0
        },
        {
            "id":18,
            "name":"OrG.rl",
            "symbolSize":10,
            "value":3,
            "label":{
                "normal":{
                    "show":true
                }
            },
            "category":3.0
        },
        {
            "id":19,
            "name":"OrG.cl",
            "symbolSize":10,
            "value":3,
            "label":{
                "normal":{
                    "show":true
                }
            },
            "category":3.0
        },
        {
            "id":20,
            "name":"M1.v",
            "symbolSize":10,
            "value":3,
            "label":{
                "normal":{
                    "show":true
                }
            },
            "category":4.0
        },
        {
            "id":21,
            "name":"M1.i",
            "symbolSize":10,
            "value":3,
            "label":{
                "normal":{
                    "show":true
                }
            },
            "category":4.0
        },
        {
            "id":22,
            "name":"M1.d",
            "symbolSize":10,
            "value":3,
            "label":{
                "normal":{
                    "show":true
                }
            },
            "category":4.0
        },
        {
            "id":23,
            "name":"M1.m",
            "symbolSize":10,
            "value":3,
            "label":{
                "normal":{
                    "show":true
                }
            },
            "category":4.0
        },
        {
            "id":24,
            "name":"PM.rd",
            "symbolSize":10,
            "value":3,
            "label":{
                "normal":{
                    "show":true
                }
            },
            "category":5.0
        },
        {
            "id":25,
            "name":"PM.cd",
            "symbolSize":10,
            "value":3,
            "label":{
                "normal":{
                    "show":true
                }
            },
            "category":5.0
        },
        {
            "id":26,
            "name":"PM.i",
            "symbolSize":10,
            "value":3,
            "label":{
                "normal":{
                    "show":true
                }
            },
            "category":5.0
        },
        {
            "id":27,
            "name":"PM.cv",
            "symbolSize":10,
            "value":3,
            "label":{
                "normal":{
                    "show":true
                }
            },
            "category":5.0
        },
        {
            "id":28,
            "name":"PM.rv",
            "symbolSize":10,
            "value":3,
            "label":{
                "normal":{
                    "show":true
                }
            },
            "category":5.0
        },
        {
            "id":29,
            "name":"PM.rm",
            "symbolSize":10,
            "value":3,
            "label":{
                "normal":{
                    "show":true
                }
            },
            "category":5.0
        },
        {
            "id":30,
            "name":"PM.cm",
            "symbolSize":10,
            "value":3,
            "label":{
                "normal":{
                    "show":true
                }
            },
            "category":5.0
        },
        {
            "id":31,
            "name":"PoCG.dm",
            "symbolSize":10,
            "value":3,
            "label":{
                "normal":{
                    "show":true
                }
            },
            "category":6.0
        },
        {
            "id":32,
            "name":"PoCG.d",
            "symbolSize":10,
            "value":3,
            "label":{
                "normal":{
                    "show":true
                }
            },
            "category":6.0
        },
        {
            "id":33,
            "name":"PoCG.i",
            "symbolSize":10,
            "value":3,
            "label":{
                "normal":{
                    "show":true
                }
            },
            "category":6.0
        },
        {
            "id":34,
            "name":"PoCG.v",
            "symbolSize":10,
            "value":3,
            "label":{
                "normal":{
                    "show":true
                }
            },
            "category":6.0
        },
        {
            "id":35,
            "name":"FPOr",
            "symbolSize":10,
            "value":3,
            "label":{
                "normal":{
                    "show":true
                }
            },
            "category":7.0
        },
        {
            "id":36,
            "name":"FPOri",
            "symbolSize":10,
            "value":3,
            "label":{
                "normal":{
                    "show":true
                }
            },
            "category":7.0
        },
        {
            "id":37,
            "name":"FPOci",
            "symbolSize":10,
            "value":3,
            "label":{
                "normal":{
                    "show":true
                }
            },
            "category":7.0
        },
        {
            "id":38,
            "name":"FPOc",
            "symbolSize":10,
            "value":3,
            "label":{
                "normal":{
                    "show":true
                }
            },
            "category":7.0
        },
        {
            "id":39,
            "name":"SPL.rv",
            "symbolSize":10,
            "value":3,
            "label":{
                "normal":{
                    "show":true
                }
            },
            "category":8.0
        },
        {
            "id":40,
            "name":"SPL.iv",
            "symbolSize":10,
            "value":3,
            "label":{
                "normal":{
                    "show":true
                }
            },
            "category":8.0
        },
        {
            "id":41,
            "name":"SPL.cv",
            "symbolSize":10,
            "value":3,
            "label":{
                "normal":{
                    "show":true
                }
            },
            "category":8.0
        },
        {
            "id":42,
            "name":"SPL.rd",
            "symbolSize":10,
            "value":3,
            "label":{
                "normal":{
                    "show":true
                }
            },
            "category":8.0
        },
        {
            "id":43,
            "name":"SPL.cd",
            "symbolSize":10,
            "value":3,
            "label":{
                "normal":{
                    "show":true
                }
            },
            "category":8.0
        },
        {
            "id":44,
            "name":"SPL.m",
            "symbolSize":10,
            "value":3,
            "label":{
                "normal":{
                    "show":true
                }
            },
            "category":8.0
        },
        {
            "id":45,
            "name":"IPL.sr",
            "symbolSize":10,
            "value":3,
            "label":{
                "normal":{
                    "show":true
                }
            },
            "category":9.0
        },
        {
            "id":46,
            "name":"IPL.sri",
            "symbolSize":10,
            "value":3,
            "label":{
                "normal":{
                    "show":true
                }
            },
            "category":9.0
        },
        {
            "id":47,
            "name":"IPL.sci",
            "symbolSize":10,
            "value":3,
            "label":{
                "normal":{
                    "show":true
                }
            },
            "category":9.0
        },
        {
            "id":48,
            "name":"IPL.sc",
            "symbolSize":10,
            "value":3,
            "label":{
                "normal":{
                    "show":true
                }
            },
            "category":9.0
        },
        {
            "id":49,
            "name":"IPL.gr",
            "symbolSize":10,
            "value":3,
            "label":{
                "normal":{
                    "show":true
                }
            },
            "category":9.0
        },
        {
            "id":50,
            "name":"IPL.gri",
            "symbolSize":10,
            "value":3,
            "label":{
                "normal":{
                    "show":true
                }
            },
            "category":9.0
        },
        {
            "id":51,
            "name":"IPL.gci",
            "symbolSize":10,
            "value":3,
            "label":{
                "normal":{
                    "show":true
                }
            },
            "category":9.0
        },
        {
            "id":52,
            "name":"IPL.gc",
            "symbolSize":10,
            "value":3,
            "label":{
                "normal":{
                    "show":true
                }
            },
            "category":9.0
        },
        {
            "id":53,
            "name":"PrCu.vr",
            "symbolSize":10,
            "value":3,
            "label":{
                "normal":{
                    "show":true
                }
            },
            "category":10.0
        },
        {
            "id":54,
            "name":"PrCu.dr",
            "symbolSize":10,
            "value":3,
            "label":{
                "normal":{
                    "show":true
                }
            },
            "category":10.0
        },
        {
            "id":55,
            "name":"PrCu.dc",
            "symbolSize":10,
            "value":3,
            "label":{
                "normal":{
                    "show":true
                }
            },
            "category":10.0
        },
        {
            "id":56,
            "name":"PrCu.di",
            "symbolSize":10,
            "value":3,
            "label":{
                "normal":{
                    "show":true
                }
            },
            "category":10.0
        },
        {
            "id":57,
            "name":"PrCu.vi",
            "symbolSize":10,
            "value":3,
            "label":{
                "normal":{
                    "show":true
                }
            },
            "category":10.0
        },
        {
            "id":58,
            "name":"PrCu.vc",
            "symbolSize":10,
            "value":3,
            "label":{
                "normal":{
                    "show":true
                }
            },
            "category":10.0
        },
        {
            "id":59,
            "name":"PrL.d",
            "symbolSize":10,
            "value":3,
            "label":{
                "normal":{
                    "show":true
                }
            },
            "category":11.0
        },
        {
            "id":60,
            "name":"PrL.i",
            "symbolSize":10,
            "value":3,
            "label":{
                "normal":{
                    "show":true
                }
            },
            "category":11.0
        },
        {
            "id":61,
            "name":"PrL.STS",
            "symbolSize":10,
            "value":3,
            "label":{
                "normal":{
                    "show":true
                }
            },
            "category":11.0
        },
        {
            "id":62,
            "name":"PrL.v",
            "symbolSize":10,
            "value":3,
            "label":{
                "normal":{
                    "show":true
                }
            },
            "category":11.0
        },
        {
            "id":63,
            "name":"SFL.r",
            "symbolSize":10,
            "value":3,
            "label":{
                "normal":{
                    "show":true
                }
            },
            "category":12.0
        },
        {
            "id":64,
            "name":"SFL.i",
            "symbolSize":10,
            "value":3,
            "label":{
                "normal":{
                    "show":true
                }
            },
            "category":12.0
        },
        {
            "id":65,
            "name":"STG.gc",
            "symbolSize":10,
            "value":3,
            "label":{
                "normal":{
                    "show":true
                }
            },
            "category":12.0
        },
        {
            "id":66,
            "name":"STG.gr",
            "symbolSize":10,
            "value":3,
            "label":{
                "normal":{
                    "show":true
                }
            },
            "category":12.0
        },
        {
            "id":67,
            "name":"STG.gri",
            "symbolSize":10,
            "value":3,
            "label":{
                "normal":{
                    "show":true
                }
            },
            "category":12.0
        },
        {
            "id":68,
            "name":"STG.gci",
            "symbolSize":10,
            "value":3,
            "label":{
                "normal":{
                    "show":true
                }
            },
            "category":12.0
        },
        {
            "id":69,
            "name":"STSU.rEx",
            "symbolSize":10,
            "value":3,
            "label":{
                "normal":{
                    "show":true
                }
            },
            "category":12.0
        },
        {
            "id":70,
            "name":"STSU.cEx",
            "symbolSize":10,
            "value":3,
            "label":{
                "normal":{
                    "show":true
                }
            },
            "category":12.0
        },
        {
            "id":71,
            "name":"STSU.r",
            "symbolSize":10,
            "value":3,
            "label":{
                "normal":{
                    "show":true
                }
            },
            "category":12.0
        },
        {
            "id":72,
            "name":"STSU.ri",
            "symbolSize":10,
            "value":3,
            "label":{
                "normal":{
                    "show":true
                }
            },
            "category":12.0
        },
        {
            "id":73,
            "name":"STSU.ci",
            "symbolSize":10,
            "value":3,
            "label":{
                "normal":{
                    "show":true
                }
            },
            "category":12.0
        },
        {
            "id":74,
            "name":"STSU.c",
            "symbolSize":10,
            "value":3,
            "label":{
                "normal":{
                    "show":true
                }
            },
            "category":12.0
        },
        {
            "id":75,
            "name":"STSL.r",
            "symbolSize":10,
            "value":3,
            "label":{
                "normal":{
                    "show":true
                }
            },
            "category":13.0
        },
        {
            "id":76,
            "name":"STSL.cIn",
            "symbolSize":10,
            "value":3,
            "label":{
                "normal":{
                    "show":true
                }
            },
            "category":13.0
        },
        {
            "id":77,
            "name":"STSL.cEx",
            "symbolSize":10,
            "value":3,
            "label":{
                "normal":{
                    "show":true
                }
            },
            "category":13.0
        },
        {
            "id":78,
            "name":"ITG.gr",
            "symbolSize":10,
            "value":3,
            "label":{
                "normal":{
                    "show":true
                }
            },
            "category":13.0
        },
        {
            "id":79,
            "name":"ITG.gdc",
            "symbolSize":10,
            "value":3,
            "label":{
                "normal":{
                    "show":true
                }
            },
            "category":13.0
        },
        {
            "id":80,
            "name":"ITG.gvc",
            "symbolSize":10,
            "value":3,
            "label":{
                "normal":{
                    "show":true
                }
            },
            "category":13.0
        },
        {
            "id":81,
            "name":"PHG.r",
            "symbolSize":10,
            "value":3,
            "label":{
                "normal":{
                    "show":true
                }
            },
            "category":14.0
        },
        {
            "id":82,
            "name":"PHG.mi",
            "symbolSize":10,
            "value":3,
            "label":{
                "normal":{
                    "show":true
                }
            },
            "category":14.0
        },
        {
            "id":83,
            "name":"PHG.li",
            "symbolSize":10,
            "value":3,
            "label":{
                "normal":{
                    "show":true
                }
            },
            "category":14.0
        },
        {
            "id":84,
            "name":"PHG.cm",
            "symbolSize":10,
            "value":3,
            "label":{
                "normal":{
                    "show":true
                }
            },
            "category":14.0
        },
        {
            "id":85,
            "name":"PHG.cl",
            "symbolSize":10,
            "value":3,
            "label":{
                "normal":{
                    "show":true
                }
            },
            "category":14.0
        },
        {
            "id":86,
            "name":"TP.vr",
            "symbolSize":10,
            "value":3,
            "label":{
                "normal":{
                    "show":true
                }
            },
            "category":15.0
        },
        {
            "id":87,
            "name":"TP.mr",
            "symbolSize":10,
            "value":3,
            "label":{
                "normal":{
                    "show":true
                }
            },
            "category":15.0
        },
        {
            "id":88,
            "name":"TP.lr",
            "symbolSize":10,
            "value":3,
            "label":{
                "normal":{
                    "show":true
                }
            },
            "category":15.0
        },
        {
            "id":89,
            "name":"TP.dr",
            "symbolSize":10,
            "value":3,
            "label":{
                "normal":{
                    "show":true
                }
            },
            "category":15.0
        },
        {
            "id":90,
            "name":"TP.cEx",
            "symbolSize":10,
            "value":3,
            "label":{
                "normal":{
                    "show":true
                }
            },
            "category":15.0
        },
        {
            "id":91,
            "name":"TP.cIn",
            "symbolSize":10,
            "value":3,
            "label":{
                "normal":{
                    "show":true
                }
            },
            "category":15.0
        },
        {
            "id":92,
            "name":"V1.cm",
            "symbolSize":10,
            "value":3,
            "label":{
                "normal":{
                    "show":true
                }
            },
            "category":16.0
        },
        {
            "id":93,
            "name":"V1.dl",
            "symbolSize":10,
            "value":3,
            "label":{
                "normal":{
                    "show":true
                }
            },
            "category":16.0
        },
        {
            "id":94,
            "name":"V1.vl",
            "symbolSize":10,
            "value":3,
            "label":{
                "normal":{
                    "show":true
                }
            },
            "category":16.0
        },
        {
            "id":95,
            "name":"V1.mvi",
            "symbolSize":10,
            "value":3,
            "label":{
                "normal":{
                    "show":true
                }
            },
            "category":16.0
        },
        {
            "id":96,
            "name":"V1.mdi",
            "symbolSize":10,
            "value":3,
            "label":{
                "normal":{
                    "show":true
                }
            },
            "category":16.0
        },
        {
            "id":97,
            "name":"V1.rm",
            "symbolSize":10,
            "value":3,
            "label":{
                "normal":{
                    "show":true
                }
            },
            "category":16.0
        },
        {
            "id":98,
            "name":"V2.l",
            "symbolSize":10,
            "value":3,
            "label":{
                "normal":{
                    "show":true
                }
            },
            "category":17.0
        },
        {
            "id":99,
            "name":"V2.d",
            "symbolSize":10,
            "value":3,
            "label":{
                "normal":{
                    "show":true
                }
            },
            "category":17.0
        },
        {
            "id":100,
            "name":"V2.v",
            "symbolSize":10,
            "value":3,
            "label":{
                "normal":{
                    "show":true
                }
            },
            "category":17.0
        },
        {
            "id":101,
            "name":"V2.dm",
            "symbolSize":10,
            "value":3,
            "label":{
                "normal":{
                    "show":true
                }
            },
            "category":17.0
        },
        {
            "id":102,
            "name":"V2.vm",
            "symbolSize":10,
            "value":3,
            "label":{
                "normal":{
                    "show":true
                }
            },
            "category":17.0
        },
        {
            "id":103,
            "name":"VMO.l",
            "symbolSize":10,
            "value":3,
            "label":{
                "normal":{
                    "show":true
                }
            },
            "category":18.0
        },
        {
            "id":104,
            "name":"VMO.i",
            "symbolSize":10,
            "value":3,
            "label":{
                "normal":{
                    "show":true
                }
            },
            "category":18.0
        },
        {
            "id":105,
            "name":"VMO.m",
            "symbolSize":10,
            "value":3,
            "label":{
                "normal":{
                    "show":true
                }
            },
            "category":18.0
        },
        {
            "id":106,
            "name":"INS.vr",
            "symbolSize":10,
            "value":3,
            "label":{
                "normal":{
                    "show":true
                }
            },
            "category":19.0
        },
        {
            "id":107,
            "name":"INS.dr",
            "symbolSize":10,
            "value":3,
            "label":{
                "normal":{
                    "show":true
                }
            },
            "category":19.0
        },
        {
            "id":108,
            "name":"INS.ri",
            "symbolSize":10,
            "value":3,
            "label":{
                "normal":{
                    "show":true
                }
            },
            "category":19.0
        },
        {
            "id":109,
            "name":"INS.v",
            "symbolSize":10,
            "value":3,
            "label":{
                "normal":{
                    "show":true
                }
            },
            "category":19.0
        },
        {
            "id":110,
            "name":"INS.ci",
            "symbolSize":10,
            "value":3,
            "label":{
                "normal":{
                    "show":true
                }
            },
            "category":19.0
        },
        {
            "id":111,
            "name":"INS.c",
            "symbolSize":10,
            "value":3,
            "label":{
                "normal":{
                    "show":true
                }
            },
            "category":19.0
        },
        {
            "id":112,
            "name":"CG.vr",
            "symbolSize":10,
            "value":3,
            "label":{
                "normal":{
                    "show":true
                }
            },
            "category":20.0
        },
        {
            "id":113,
            "name":"CG.ir",
            "symbolSize":10,
            "value":3,
            "label":{
                "normal":{
                    "show":true
                }
            },
            "category":20.0
        },
        {
            "id":114,
            "name":"CG.dr",
            "symbolSize":10,
            "value":3,
            "label":{
                "normal":{
                    "show":true
                }
            },
            "category":20.0
        },
        {
            "id":115,
            "name":"CG.idr",
            "symbolSize":10,
            "value":3,
            "label":{
                "normal":{
                    "show":true
                }
            },
            "category":20.0
        },
        {
            "id":116,
            "name":"CG.idc",
            "symbolSize":10,
            "value":3,
            "label":{
                "normal":{
                    "show":true
                }
            },
            "category":20.0
        },
        {
            "id":117,
            "name":"CG.ivr",
            "symbolSize":10,
            "value":3,
            "label":{
                "normal":{
                    "show":true
                }
            },
            "category":20.0
        },
        {
            "id":118,
            "name":"CG.ivc",
            "symbolSize":10,
            "value":3,
            "label":{
                "normal":{
                    "show":true
                }
            },
            "category":20.0
        },
        {
            "id":119,
            "name":"CG.dc",
            "symbolSize":10,
            "value":3,
            "label":{
                "normal":{
                    "show":true
                }
            },
            "category":20.0
        },
        {
            "id":120,
            "name":"CG.vc",
            "symbolSize":10,
            "value":3,
            "label":{
                "normal":{
                    "show":true
                }
            },
            "category":20.0
        },
        {
            "id":121,
            "name":"CG.RSr",
            "symbolSize":10,
            "value":3,
            "label":{
                "normal":{
                    "show":true
                }
            },
            "category":20.0
        },
        {
            "id":122,
            "name":"CG.Rsi",
            "symbolSize":10,
            "value":3,
            "label":{
                "normal":{
                    "show":true
                }
            },
            "category":20.0
        },
        {
            "id":123,
            "name":"CG.RSc",
            "symbolSize":10,
            "value":3,
            "label":{
                "normal":{
                    "show":true
                }
            },
            "category":20.0
        },
        {
            "id":124,
            "name":"Acb.C",
            "symbolSize":10,
            "value":3,
            "label":{
                "normal":{
                    "show":true
                }
            },
            "category":21.0
        },
        {
            "id":125,
            "name":"Acb.Sh",
            "symbolSize":10,
            "value":3,
            "label":{
                "normal":{
                    "show":true
                }
            },
            "category":21.0
        },
        {
            "id":126,
            "name":"Amyg.cl",
            "symbolSize":10,
            "value":3,
            "label":{
                "normal":{
                    "show":true
                }
            },
            "category":22.0
        },
        {
            "id":127,
            "name":"Amyg.rl",
            "symbolSize":10,
            "value":3,
            "label":{
                "normal":{
                    "show":true
                }
            },
            "category":22.0
        },
        {
            "id":128,
            "name":"Amyg.m",
            "symbolSize":10,
            "value":3,
            "label":{
                "normal":{
                    "show":true
                }
            },
            "category":22.0
        },
        {
            "id":129,
            "name":"Cd.Hv",
            "symbolSize":10,
            "value":3,
            "label":{
                "normal":{
                    "show":true
                }
            },
            "category":23.0
        },
        {
            "id":130,
            "name":"Cd.B",
            "symbolSize":10,
            "value":3,
            "label":{
                "normal":{
                    "show":true
                }
            },
            "category":23.0
        },
        {
            "id":131,
            "name":"Cd.Hi",
            "symbolSize":10,
            "value":3,
            "label":{
                "normal":{
                    "show":true
                }
            },
            "category":23.0
        },
        {
            "id":132,
            "name":"Cd.Hd",
            "symbolSize":10,
            "value":3,
            "label":{
                "normal":{
                    "show":true
                }
            },
            "category":23.0
        },
        {
            "id":133,
            "name":"Cd.T",
            "symbolSize":10,
            "value":3,
            "label":{
                "normal":{
                    "show":true
                }
            },
            "category":23.0
        },
        {
            "id":134,
            "name":"HF.c",
            "symbolSize":10,
            "value":3,
            "label":{
                "normal":{
                    "show":true
                }
            },
            "category":24.0
        },
        {
            "id":135,
            "name":"HF.i",
            "symbolSize":10,
            "value":3,
            "label":{
                "normal":{
                    "show":true
                }
            },
            "category":24.0
        },
        {
            "id":136,
            "name":"HF.r",
            "symbolSize":10,
            "value":3,
            "label":{
                "normal":{
                    "show":true
                }
            },
            "category":24.0
        },
        {
            "id":137,
            "name":"Hy.cl",
            "symbolSize":10,
            "value":3,
            "label":{
                "normal":{
                    "show":true
                }
            },
            "category":25.0
        },
        {
            "id":138,
            "name":"Hy.rl",
            "symbolSize":10,
            "value":3,
            "label":{
                "normal":{
                    "show":true
                }
            },
            "category":25.0
        },
        {
            "id":139,
            "name":"Hy.m",
            "symbolSize":10,
            "value":3,
            "label":{
                "normal":{
                    "show":true
                }
            },
            "category":25.0
        },
        {
            "id":140,
            "name":"GP.v",
            "symbolSize":10,
            "value":3,
            "label":{
                "normal":{
                    "show":true
                }
            },
            "category":26.0
        },
        {
            "id":141,
            "name":"GP.d",
            "symbolSize":10,
            "value":3,
            "label":{
                "normal":{
                    "show":true
                }
            },
            "category":26.0
        },
        {
            "id":142,
            "name":"Pu.r",
            "symbolSize":10,
            "value":3,
            "label":{
                "normal":{
                    "show":true
                }
            },
            "category":27.0
        },
        {
            "id":143,
            "name":"Pu.v",
            "symbolSize":10,
            "value":3,
            "label":{
                "normal":{
                    "show":true
                }
            },
            "category":27.0
        },
        {
            "id":144,
            "name":"Pu.c",
            "symbolSize":10,
            "value":3,
            "label":{
                "normal":{
                    "show":true
                }
            },
            "category":27.0
        },
        {
            "id":145,
            "name":"Tha.rv",
            "symbolSize":10,
            "value":3,
            "label":{
                "normal":{
                    "show":true
                }
            },
            "category":28.0
        },
        {
            "id":146,
            "name":"Tha.c",
            "symbolSize":10,
            "value":3,
            "label":{
                "normal":{
                    "show":true
                }
            },
            "category":28.0
        },
        {
            "id":147,
            "name":"Tha.ld",
            "symbolSize":10,
            "value":3,
            "label":{
                "normal":{
                    "show":true
                }
            },
            "category":28.0
        },
        {
            "id":148,
            "name":"Tha.l",
            "symbolSize":10,
            "value":3,
            "label":{
                "normal":{
                    "show":true
                }
            },
            "category":28.0
        },
        {
            "id":149,
            "name":"Tha.m",
            "symbolSize":10,
            "value":3,
            "label":{
                "normal":{
                    "show":true
                }
            },
            "category":28.0
        },
        {
            "id":150,
            "name":"Tha.Sh",
            "symbolSize":10,
            "value":3,
            "label":{
                "normal":{
                    "show":true
                }
            },
            "category":28.0
        },
        {
            "id":151,
            "name":"Tha.cv",
            "symbolSize":10,
            "value":3,
            "label":{
                "normal":{
                    "show":true
                }
            },
            "category":28.0
        }
    ],
    "links":[
        {
            "id":0,
            "source":71,
            "target":0,
            "value":0.14558240720055068,
            "lineStyle":{
                "width":0.14558240720055068,
                "opacity":0.5,
                "curveness":0.3
            },
            "symbolSize":1.455824072005507
        },
        {
            "id":1,
            "source":71,
            "target":1,
            "value":0.10970392854337485,
            "lineStyle":{
                "width":0.10970392854337485,
                "opacity":0.5,
                "curveness":0.3
            },
            "symbolSize":1.0970392854337485
        },
        {
            "id":2,
            "source":71,
            "target":2,
            "value":0.20847946030549572,
            "lineStyle":{
                "width":0.20847946030549572,
                "opacity":0.5,
                "curveness":0.3
            },
            "symbolSize":2.084794603054957
        },
        {
            "id":3,
            "source":71,
            "target":3,
            "value":0.032793348041173884,
            "lineStyle":{
                "width":0.032793348041173884,
                "opacity":0.5,
                "curveness":0.3
            },
            "symbolSize":0.32793348041173886
        },
        {
            "id":5,
            "source":71,
            "target":5,
            "value":0.15401579416050967,
            "lineStyle":{
                "width":0.15401579416050967,
                "opacity":0.5,
                "curveness":0.3
            },
            "symbolSize":1.5401579416050968
        },
        {
            "id":6,
            "source":71,
            "target":6,
            "value":0.11100429466768927,
            "lineStyle":{
                "width":0.11100429466768927,
                "opacity":0.5,
                "curveness":0.3
            },
            "symbolSize":1.1100429466768926
        },
        {
            "id":7,
            "source":71,
            "target":7,
            "value":0.012291922587963596,
            "lineStyle":{
                "width":0.012291922587963596,
                "opacity":0.5,
                "curveness":0.3
            },
            "symbolSize":0.12291922587963597
        },
        {
            "id":8,
            "source":71,
            "target":8,
            "value":0.007755339689343304,
            "lineStyle":{
                "width":0.007755339689343304,
                "opacity":0.5,
                "curveness":0.3
            },
            "symbolSize":0.07755339689343303
        },
        {
            "id":9,
            "source":71,
            "target":9,
            "value":0.20898466976521737,
            "lineStyle":{
                "width":0.20898466976521737,
                "opacity":0.5,
                "curveness":0.3
            },
            "symbolSize":2.089846697652174
        },
        {
            "id":10,
            "source":71,
            "target":10,
            "value":0.10128733796983425,
            "lineStyle":{
                "width":0.10128733796983425,
                "opacity":0.5,
                "curveness":0.3
            },
            "symbolSize":1.0128733796983425
        },
        {
            "id":12,
            "source":71,
            "target":12,
            "value":0.03212344870895294,
            "lineStyle":{
                "width":0.03212344870895294,
                "opacity":0.5,
                "curveness":0.3
            },
            "symbolSize":0.3212344870895294
        },
        {
            "id":13,
            "source":71,
            "target":13,
            "value":0.13827067903392135,
            "lineStyle":{
                "width":0.13827067903392135,
                "opacity":0.5,
                "curveness":0.3
            },
            "symbolSize":1.3827067903392134
        },
        {
            "id":14,
            "source":71,
            "target":14,
            "value":0.11376633564824444,
            "lineStyle":{
                "width":0.11376633564824444,
                "opacity":0.5,
                "curveness":0.3
            },
            "symbolSize":1.1376633564824443
        },
        {
            "id":15,
            "source":71,
            "target":15,
            "value":0.2536314269255617,
            "lineStyle":{
                "width":0.2536314269255617,
                "opacity":0.5,
                "curveness":0.3
            },
            "symbolSize":2.536314269255617
        },
        {
            "id":16,
            "source":71,
            "target":16,
            "value":0.26717686224540016,
            "lineStyle":{
                "width":0.26717686224540016,
                "opacity":0.5,
                "curveness":0.3
            },
            "symbolSize":2.6717686224540014
        },
        {
            "id":17,
            "source":71,
            "target":17,
            "value":0.5410255405405298,
            "lineStyle":{
                "width":0.5410255405405298,
                "opacity":0.5,
                "curveness":0.3
            },
            "symbolSize":5.410255405405298
        },
        {
            "id":18,
            "source":71,
            "target":18,
            "value":0.2276700482525513,
            "lineStyle":{
                "width":0.2276700482525513,
                "opacity":0.5,
                "curveness":0.3
            },
            "symbolSize":2.276700482525513
        },
        {
            "id":19,
            "source":71,
            "target":19,
            "value":0.41839880733814583,
            "lineStyle":{
                "width":0.41839880733814583,
                "opacity":0.5,
                "curveness":0.3
            },
            "symbolSize":4.1839880733814585
        },
        {
            "id":22,
            "source":71,
            "target":22,
            "value":0.015510679378686608,
            "lineStyle":{
                "width":0.015510679378686608,
                "opacity":0.5,
                "curveness":0.3
            },
            "symbolSize":0.15510679378686607
        },
        {
            "id":24,
            "source":71,
            "target":24,
            "value":0.007755339689343304,
            "lineStyle":{
                "width":0.007755339689343304,
                "opacity":0.5,
                "curveness":0.3
            },
            "symbolSize":0.07755339689343303
        },
        {
            "id":26,
            "source":71,
            "target":26,
            "value":0.007755339689343304,
            "lineStyle":{
                "width":0.007755339689343304,
                "opacity":0.5,
                "curveness":0.3
            },
            "symbolSize":0.07755339689343303
        },
        {
            "id":28,
            "source":71,
            "target":28,
            "value":0.025110943486508087,
            "lineStyle":{
                "width":0.025110943486508087,
                "opacity":0.5,
                "curveness":0.3
            },
            "symbolSize":0.25110943486508086
        },
        {
            "id":30,
            "source":71,
            "target":30,
            "value":0.008086650983255344,
            "lineStyle":{
                "width":0.008086650983255344,
                "opacity":0.5,
                "curveness":0.3
            },
            "symbolSize":0.08086650983255345
        },
        {
            "id":31,
            "source":71,
            "target":31,
            "value":0.007755339689343304,
            "lineStyle":{
                "width":0.007755339689343304,
                "opacity":0.5,
                "curveness":0.3
            },
            "symbolSize":0.07755339689343303
        },
        {
            "id":32,
            "source":71,
            "target":32,
            "value":0.012291922587963596,
            "lineStyle":{
                "width":0.012291922587963596,
                "opacity":0.5,
                "curveness":0.3
            },
            "symbolSize":0.12291922587963597
        },
        {
            "id":33,
            "source":71,
            "target":33,
            "value":0.007755339689343304,
            "lineStyle":{
                "width":0.007755339689343304,
                "opacity":0.5,
                "curveness":0.3
            },
            "symbolSize":0.07755339689343303
        },
        {
            "id":34,
            "source":71,
            "target":34,
            "value":0.012291922587963596,
            "lineStyle":{
                "width":0.012291922587963596,
                "opacity":0.5,
                "curveness":0.3
            },
            "symbolSize":0.12291922587963597
        },
        {
            "id":35,
            "source":71,
            "target":35,
            "value":0.12795259906674433,
            "lineStyle":{
                "width":0.12795259906674433,
                "opacity":0.5,
                "curveness":0.3
            },
            "symbolSize":1.2795259906674432
        },
        {
            "id":36,
            "source":71,
            "target":36,
            "value":0.03554410443694029,
            "lineStyle":{
                "width":0.03554410443694029,
                "opacity":0.5,
                "curveness":0.3
            },
            "symbolSize":0.3554410443694029
        },
        {
            "id":37,
            "source":71,
            "target":37,
            "value":0.03179015508137599,
            "lineStyle":{
                "width":0.03179015508137599,
                "opacity":0.5,
                "curveness":0.3
            },
            "symbolSize":0.3179015508137599
        },
        {
            "id":38,
            "source":71,
            "target":38,
            "value":0.04406679525760063,
            "lineStyle":{
                "width":0.04406679525760063,
                "opacity":0.5,
                "curveness":0.3
            },
            "symbolSize":0.44066795257600627
        },
        {
            "id":39,
            "source":71,
            "target":39,
            "value":0.007755339689343304,
            "lineStyle":{
                "width":0.007755339689343304,
                "opacity":0.5,
                "curveness":0.3
            },
            "symbolSize":0.07755339689343303
        },
        {
            "id":40,
            "source":71,
            "target":40,
            "value":0.015164280152430654,
            "lineStyle":{
                "width":0.015164280152430654,
                "opacity":0.5,
                "curveness":0.3
            },
            "symbolSize":0.15164280152430654
        },
        {
            "id":41,
            "source":71,
            "target":41,
            "value":0.012291922587963596,
            "lineStyle":{
                "width":0.012291922587963596,
                "opacity":0.5,
                "curveness":0.3
            },
            "symbolSize":0.12291922587963597
        },
        {
            "id":42,
            "source":71,
            "target":42,
            "value":0.014817880926174701,
            "lineStyle":{
                "width":0.014817880926174701,
                "opacity":0.5,
                "curveness":0.3
            },
            "symbolSize":0.148178809261747
        },
        {
            "id":43,
            "source":71,
            "target":43,
            "value":0.015841990672598647,
            "lineStyle":{
                "width":0.015841990672598647,
                "opacity":0.5,
                "curveness":0.3
            },
            "symbolSize":0.15841990672598646
        },
        {
            "id":45,
            "source":71,
            "target":45,
            "value":0.007755339689343304,
            "lineStyle":{
                "width":0.007755339689343304,
                "opacity":0.5,
                "curveness":0.3
            },
            "symbolSize":0.07755339689343303
        },
        {
            "id":46,
            "source":71,
            "target":46,
            "value":0.025416281573168595,
            "lineStyle":{
                "width":0.025416281573168595,
                "opacity":0.5,
                "curveness":0.3
            },
            "symbolSize":0.254162815731686
        },
        {
            "id":47,
            "source":71,
            "target":47,
            "value":0.014817880926174701,
            "lineStyle":{
                "width":0.014817880926174701,
                "opacity":0.5,
                "curveness":0.3
            },
            "symbolSize":0.148178809261747
        },
        {
            "id":48,
            "source":71,
            "target":48,
            "value":0.0348663939167723,
            "lineStyle":{
                "width":0.0348663939167723,
                "opacity":0.5,
                "curveness":0.3
            },
            "symbolSize":0.348663939167723
        },
        {
            "id":50,
            "source":71,
            "target":50,
            "value":0.015510679378686608,
            "lineStyle":{
                "width":0.015510679378686608,
                "opacity":0.5,
                "curveness":0.3
            },
            "symbolSize":0.15510679378686607
        },
        {
            "id":51,
            "source":71,
            "target":51,
            "value":0.03458440702393028,
            "lineStyle":{
                "width":0.03458440702393028,
                "opacity":0.5,
                "curveness":0.3
            },
            "symbolSize":0.3458440702393028
        },
        {
            "id":52,
            "source":71,
            "target":52,
            "value":0.0200472622773069,
            "lineStyle":{
                "width":0.0200472622773069,
                "opacity":0.5,
                "curveness":0.3
            },
            "symbolSize":0.200472622773069
        },
        {
            "id":55,
            "source":71,
            "target":55,
            "value":0.042311988167433486,
            "lineStyle":{
                "width":0.042311988167433486,
                "opacity":0.5,
                "curveness":0.3
            },
            "symbolSize":0.42311988167433484
        },
        {
            "id":57,
            "source":71,
            "target":57,
            "value":0.03203613418356005,
            "lineStyle":{
                "width":0.03203613418356005,
                "opacity":0.5,
                "curveness":0.3
            },
            "symbolSize":0.3203613418356005
        },
        {
            "id":58,
            "source":71,
            "target":58,
            "value":0.04529724770285075,
            "lineStyle":{
                "width":0.04529724770285075,
                "opacity":0.5,
                "curveness":0.3
            },
            "symbolSize":0.4529724770285075
        },
        {
            "id":59,
            "source":71,
            "target":59,
            "value":0.0886736791287415,
            "lineStyle":{
                "width":0.0886736791287415,
                "opacity":0.5,
                "curveness":0.3
            },
            "symbolSize":0.8867367912874149
        },
        {
            "id":60,
            "source":71,
            "target":60,
            "value":0.1900405198780689,
            "lineStyle":{
                "width":0.1900405198780689,
                "opacity":0.5,
                "curveness":0.3
            },
            "symbolSize":1.900405198780689
        },
        {
            "id":61,
            "source":71,
            "target":61,
            "value":0.2543078171989511,
            "lineStyle":{
                "width":0.2543078171989511,
                "opacity":0.5,
                "curveness":0.3
            },
            "symbolSize":2.543078171989511
        },
        {
            "id":62,
            "source":71,
            "target":62,
            "value":0.19091475618543882,
            "lineStyle":{
                "width":0.19091475618543882,
                "opacity":0.5,
                "curveness":0.3
            },
            "symbolSize":1.9091475618543883
        },
        {
            "id":63,
            "source":71,
            "target":63,
            "value":0.6143627356947874,
            "lineStyle":{
                "width":0.6143627356947874,
                "opacity":0.5,
                "curveness":0.3
            },
            "symbolSize":6.143627356947874
        },
        {
            "id":64,
            "source":71,
            "target":64,
            "value":0.17979665792237132,
            "lineStyle":{
                "width":0.17979665792237132,
                "opacity":0.5,
                "curveness":0.3
            },
            "symbolSize":1.7979665792237132
        },
        {
            "id":65,
            "source":71,
            "target":65,
            "value":0.15088711880847097,
            "lineStyle":{
                "width":0.15088711880847097,
                "opacity":0.5,
                "curveness":0.3
            },
            "symbolSize":1.5088711880847097
        },
        {
            "id":66,
            "source":71,
            "target":66,
            "value":0.7206000420462348,
            "lineStyle":{
                "width":0.7206000420462348,
                "opacity":0.5,
                "curveness":0.3
            },
            "symbolSize":7.206000420462349
        },
        {
            "id":67,
            "source":71,
            "target":67,
            "value":0.5535734369605319,
            "lineStyle":{
                "width":0.5535734369605319,
                "opacity":0.5,
                "curveness":0.3
            },
            "symbolSize":5.5357343696053185
        },
        {
            "id":68,
            "source":71,
            "target":68,
            "value":0.2741174222822203,
            "lineStyle":{
                "width":0.2741174222822203,
                "opacity":0.5,
                "curveness":0.3
            },
            "symbolSize":2.741174222822203
        },
        {
            "id":69,
            "source":71,
            "target":69,
            "value":0.7132144530435487,
            "lineStyle":{
                "width":0.7132144530435487,
                "opacity":0.5,
                "curveness":0.3
            },
            "symbolSize":7.132144530435487
        },
        {
            "id":70,
            "source":71,
            "target":70,
            "value":0.41487334350194016,
            "lineStyle":{
                "width":0.41487334350194016,
                "opacity":0.5,
                "curveness":0.3
            },
            "symbolSize":4.148733435019402
        },
        {
            "id":72,
            "source":71,
            "target":72,
            "value":0.7804565812872782,
            "lineStyle":{
                "width":0.7804565812872782,
                "opacity":0.5,
                "curveness":0.3
            },
            "symbolSize":7.804565812872783
        },
        {
            "id":73,
            "source":71,
            "target":73,
            "value":0.3601190739866223,
            "lineStyle":{
                "width":0.3601190739866223,
                "opacity":0.5,
                "curveness":0.3
            },
            "symbolSize":3.601190739866223
        },
        {
            "id":74,
            "source":71,
            "target":74,
            "value":0.12538995792761976,
            "lineStyle":{
                "width":0.12538995792761976,
                "opacity":0.5,
                "curveness":0.3
            },
            "symbolSize":1.2538995792761976
        },
        {
            "id":75,
            "source":71,
            "target":75,
            "value":0.7647275531348884,
            "lineStyle":{
                "width":0.7647275531348884,
                "opacity":0.5,
                "curveness":0.3
            },
            "symbolSize":7.647275531348884
        },
        {
            "id":76,
            "source":71,
            "target":76,
            "value":0.42058590530973994,
            "lineStyle":{
                "width":0.42058590530973994,
                "opacity":0.5,
                "curveness":0.3
            },
            "symbolSize":4.2058590530974
        },
        {
            "id":77,
            "source":71,
            "target":77,
            "value":0.3032874712359048,
            "lineStyle":{
                "width":0.3032874712359048,
                "opacity":0.5,
                "curveness":0.3
            },
            "symbolSize":3.0328747123590483
        },
        {
            "id":78,
            "source":71,
            "target":78,
            "value":0.8111848524905841,
            "lineStyle":{
                "width":0.8111848524905841,
                "opacity":0.5,
                "curveness":0.3
            },
            "symbolSize":8.111848524905842
        },
        {
            "id":79,
            "source":71,
            "target":79,
            "value":0.6120662495377547,
            "lineStyle":{
                "width":0.6120662495377547,
                "opacity":0.5,
                "curveness":0.3
            },
            "symbolSize":6.120662495377546
        },
        {
            "id":80,
            "source":71,
            "target":80,
            "value":0.5777658169946222,
            "lineStyle":{
                "width":0.5777658169946222,
                "opacity":0.5,
                "curveness":0.3
            },
            "symbolSize":5.777658169946221
        },
        {
            "id":81,
            "source":71,
            "target":81,
            "value":0.5946724606972535,
            "lineStyle":{
                "width":0.5946724606972535,
                "opacity":0.5,
                "curveness":0.3
            },
            "symbolSize":5.946724606972536
        },
        {
            "id":82,
            "source":71,
            "target":82,
            "value":0.34680423515682246,
            "lineStyle":{
                "width":0.34680423515682246,
                "opacity":0.5,
                "curveness":0.3
            },
            "symbolSize":3.468042351568225
        },
        {
            "id":83,
            "source":71,
            "target":83,
            "value":0.5075568830202675,
            "lineStyle":{
                "width":0.5075568830202675,
                "opacity":0.5,
                "curveness":0.3
            },
            "symbolSize":5.075568830202675
        },
        {
            "id":84,
            "source":71,
            "target":84,
            "value":0.32403490093116316,
            "lineStyle":{
                "width":0.32403490093116316,
                "opacity":0.5,
                "curveness":0.3
            },
            "symbolSize":3.2403490093116316
        },
        {
            "id":85,
            "source":71,
            "target":85,
            "value":0.5046540374430362,
            "lineStyle":{
                "width":0.5046540374430362,
                "opacity":0.5,
                "curveness":0.3
            },
            "symbolSize":5.046540374430362
        },
        {
            "id":86,
            "source":71,
            "target":86,
            "value":0.7460326739978254,
            "lineStyle":{
                "width":0.7460326739978254,
                "opacity":0.5,
                "curveness":0.3
            },
            "symbolSize":7.460326739978253
        },
        {
            "id":87,
            "source":71,
            "target":87,
            "value":0.561708084714906,
            "lineStyle":{
                "width":0.561708084714906,
                "opacity":0.5,
                "curveness":0.3
            },
            "symbolSize":5.61708084714906
        },
        {
            "id":88,
            "source":71,
            "target":88,
            "value":0.8180967424609942,
            "lineStyle":{
                "width":0.8180967424609942,
                "opacity":0.5,
                "curveness":0.3
            },
            "symbolSize":8.180967424609943
        },
        {
            "id":89,
            "source":71,
            "target":89,
            "value":0.588825838529463,
            "lineStyle":{
                "width":0.588825838529463,
                "opacity":0.5,
                "curveness":0.3
            },
            "symbolSize":5.88825838529463
        },
        {
            "id":90,
            "source":71,
            "target":90,
            "value":0.3777942641484281,
            "lineStyle":{
                "width":0.3777942641484281,
                "opacity":0.5,
                "curveness":0.3
            },
            "symbolSize":3.777942641484281
        },
        {
            "id":91,
            "source":71,
            "target":91,
            "value":0.38021318760885897,
            "lineStyle":{
                "width":0.38021318760885897,
                "opacity":0.5,
                "curveness":0.3
            },
            "symbolSize":3.80213187608859
        },
        {
            "id":92,
            "source":71,
            "target":92,
            "value":0.12555875728340882,
            "lineStyle":{
                "width":0.12555875728340882,
                "opacity":0.5,
                "curveness":0.3
            },
            "symbolSize":1.2555875728340882
        },
        {
            "id":93,
            "source":71,
            "target":93,
            "value":0.2029155040842606,
            "lineStyle":{
                "width":0.2029155040842606,
                "opacity":0.5,
                "curveness":0.3
            },
            "symbolSize":2.029155040842606
        },
        {
            "id":94,
            "source":71,
            "target":94,
            "value":0.3106550257910506,
            "lineStyle":{
                "width":0.3106550257910506,
                "opacity":0.5,
                "curveness":0.3
            },
            "symbolSize":3.1065502579105058
        },
        {
            "id":95,
            "source":71,
            "target":95,
            "value":0.408748515303117,
            "lineStyle":{
                "width":0.408748515303117,
                "opacity":0.5,
                "curveness":0.3
            },
            "symbolSize":4.08748515303117
        },
        {
            "id":96,
            "source":71,
            "target":96,
            "value":0.28513354113014405,
            "lineStyle":{
                "width":0.28513354113014405,
                "opacity":0.5,
                "curveness":0.3
            },
            "symbolSize":2.8513354113014406
        },
        {
            "id":97,
            "source":71,
            "target":97,
            "value":0.2358104872566975,
            "lineStyle":{
                "width":0.2358104872566975,
                "opacity":0.5,
                "curveness":0.3
            },
            "symbolSize":2.358104872566975
        },
        {
            "id":98,
            "source":71,
            "target":98,
            "value":0.14204222223393437,
            "lineStyle":{
                "width":0.14204222223393437,
                "opacity":0.5,
                "curveness":0.3
            },
            "symbolSize":1.4204222223393437
        },
        {
            "id":99,
            "source":71,
            "target":99,
            "value":0.0676335202524466,
            "lineStyle":{
                "width":0.0676335202524466,
                "opacity":0.5,
                "curveness":0.3
            },
            "symbolSize":0.676335202524466
        },
        {
            "id":100,
            "source":71,
            "target":100,
            "value":0.3506239562250867,
            "lineStyle":{
                "width":0.3506239562250867,
                "opacity":0.5,
                "curveness":0.3
            },
            "symbolSize":3.506239562250867
        },
        {
            "id":101,
            "source":71,
            "target":101,
            "value":0.03632673797999628,
            "lineStyle":{
                "width":0.03632673797999628,
                "opacity":0.5,
                "curveness":0.3
            },
            "symbolSize":0.3632673797999628
        },
        {
            "id":102,
            "source":71,
            "target":102,
            "value":0.45868308012093756,
            "lineStyle":{
                "width":0.45868308012093756,
                "opacity":0.5,
                "curveness":0.3
            },
            "symbolSize":4.586830801209375
        },
        {
            "id":103,
            "source":71,
            "target":103,
            "value":0.2831168360786326,
            "lineStyle":{
                "width":0.2831168360786326,
                "opacity":0.5,
                "curveness":0.3
            },
            "symbolSize":2.831168360786326
        },
        {
            "id":104,
            "source":71,
            "target":104,
            "value":0.486630065137205,
            "lineStyle":{
                "width":0.486630065137205,
                "opacity":0.5,
                "curveness":0.3
            },
            "symbolSize":4.86630065137205
        },
        {
            "id":105,
            "source":71,
            "target":105,
            "value":0.45396842443484703,
            "lineStyle":{
                "width":0.45396842443484703,
                "opacity":0.5,
                "curveness":0.3
            },
            "symbolSize":4.539684244348471
        },
        {
            "id":106,
            "source":71,
            "target":106,
            "value":0.45836700900740723,
            "lineStyle":{
                "width":0.45836700900740723,
                "opacity":0.5,
                "curveness":0.3
            },
            "symbolSize":4.583670090074072
        },
        {
            "id":107,
            "source":71,
            "target":107,
            "value":0.31295112363285427,
            "lineStyle":{
                "width":0.31295112363285427,
                "opacity":0.5,
                "curveness":0.3
            },
            "symbolSize":3.1295112363285424
        },
        {
            "id":108,
            "source":71,
            "target":108,
            "value":0.0508299857580716,
            "lineStyle":{
                "width":0.0508299857580716,
                "opacity":0.5,
                "curveness":0.3
            },
            "symbolSize":0.508299857580716
        },
        {
            "id":109,
            "source":71,
            "target":109,
            "value":0.3873428972619104,
            "lineStyle":{
                "width":0.3873428972619104,
                "opacity":0.5,
                "curveness":0.3
            },
            "symbolSize":3.873428972619104
        },
        {
            "id":110,
            "source":71,
            "target":110,
            "value":0.019829543787324433,
            "lineStyle":{
                "width":0.019829543787324433,
                "opacity":0.5,
                "curveness":0.3
            },
            "symbolSize":0.19829543787324433
        },
        {
            "id":111,
            "source":71,
            "target":111,
            "value":0.11705251282862023,
            "lineStyle":{
                "width":0.11705251282862023,
                "opacity":0.5,
                "curveness":0.3
            },
            "symbolSize":1.1705251282862021
        },
        {
            "id":112,
            "source":71,
            "target":112,
            "value":0.0912561291642294,
            "lineStyle":{
                "width":0.0912561291642294,
                "opacity":0.5,
                "curveness":0.3
            },
            "symbolSize":0.912561291642294
        },
        {
            "id":113,
            "source":71,
            "target":113,
            "value":0.1580437734772193,
            "lineStyle":{
                "width":0.1580437734772193,
                "opacity":0.5,
                "curveness":0.3
            },
            "symbolSize":1.580437734772193
        },
        {
            "id":114,
            "source":71,
            "target":114,
            "value":0.0669867054723988,
            "lineStyle":{
                "width":0.0669867054723988,
                "opacity":0.5,
                "curveness":0.3
            },
            "symbolSize":0.669867054723988
        },
        {
            "id":117,
            "source":71,
            "target":117,
            "value":0.07544208998419069,
            "lineStyle":{
                "width":0.07544208998419069,
                "opacity":0.5,
                "curveness":0.3
            },
            "symbolSize":0.7544208998419069
        },
        {
            "id":118,
            "source":71,
            "target":118,
            "value":0.007408940463087351,
            "lineStyle":{
                "width":0.007408940463087351,
                "opacity":0.5,
                "curveness":0.3
            },
            "symbolSize":0.0740894046308735
        },
        {
            "id":119,
            "source":71,
            "target":119,
            "value":0.02757199920674027,
            "lineStyle":{
                "width":0.02757199920674027,
                "opacity":0.5,
                "curveness":0.3
            },
            "symbolSize":0.2757199920674027
        },
        {
            "id":120,
            "source":71,
            "target":120,
            "value":0.02323601308302104,
            "lineStyle":{
                "width":0.02323601308302104,
                "opacity":0.5,
                "curveness":0.3
            },
            "symbolSize":0.2323601308302104
        },
        {
            "id":121,
            "source":71,
            "target":121,
            "value":0.007755339689343304,
            "lineStyle":{
                "width":0.007755339689343304,
                "opacity":0.5,
                "curveness":0.3
            },
            "symbolSize":0.07755339689343303
        },
        {
            "id":122,
            "source":71,
            "target":122,
            "value":0.039492906865311345,
            "lineStyle":{
                "width":0.039492906865311345,
                "opacity":0.5,
                "curveness":0.3
            },
            "symbolSize":0.39492906865311345
        },
        {
            "id":123,
            "source":71,
            "target":123,
            "value":0.043197271609869345,
            "lineStyle":{
                "width":0.043197271609869345,
                "opacity":0.5,
                "curveness":0.3
            },
            "symbolSize":0.4319727160986935
        },
        {
            "id":124,
            "source":71,
            "target":124,
            "value":0.27614501466024843,
            "lineStyle":{
                "width":0.27614501466024843,
                "opacity":0.5,
                "curveness":0.3
            },
            "symbolSize":2.7614501466024843
        },
        {
            "id":125,
            "source":71,
            "target":125,
            "value":0.2724896545179919,
            "lineStyle":{
                "width":0.2724896545179919,
                "opacity":0.5,
                "curveness":0.3
            },
            "symbolSize":2.724896545179919
        },
        {
            "id":126,
            "source":71,
            "target":126,
            "value":0.3959632984034614,
            "lineStyle":{
                "width":0.3959632984034614,
                "opacity":0.5,
                "curveness":0.3
            },
            "symbolSize":3.959632984034614
        },
        {
            "id":127,
            "source":71,
            "target":127,
            "value":0.4868189739666603,
            "lineStyle":{
                "width":0.4868189739666603,
                "opacity":0.5,
                "curveness":0.3
            },
            "symbolSize":4.868189739666603
        },
        {
            "id":128,
            "source":71,
            "target":128,
            "value":0.14186711506217664,
            "lineStyle":{
                "width":0.14186711506217664,
                "opacity":0.5,
                "curveness":0.3
            },
            "symbolSize":1.4186711506217664
        },
        {
            "id":129,
            "source":71,
            "target":129,
            "value":0.28886872514258066,
            "lineStyle":{
                "width":0.28886872514258066,
                "opacity":0.5,
                "curveness":0.3
            },
            "symbolSize":2.8886872514258064
        },
        {
            "id":130,
            "source":71,
            "target":130,
            "value":0.204128924748307,
            "lineStyle":{
                "width":0.204128924748307,
                "opacity":0.5,
                "curveness":0.3
            },
            "symbolSize":2.04128924748307
        },
        {
            "id":131,
            "source":71,
            "target":131,
            "value":0.12797475274816858,
            "lineStyle":{
                "width":0.12797475274816858,
                "opacity":0.5,
                "curveness":0.3
            },
            "symbolSize":1.2797475274816859
        },
        {
            "id":132,
            "source":71,
            "target":132,
            "value":0.0819343133791996,
            "lineStyle":{
                "width":0.0819343133791996,
                "opacity":0.5,
                "curveness":0.3
            },
            "symbolSize":0.819343133791996
        },
        {
            "id":133,
            "source":71,
            "target":133,
            "value":0.5551342145555529,
            "lineStyle":{
                "width":0.5551342145555529,
                "opacity":0.5,
                "curveness":0.3
            },
            "symbolSize":5.5513421455555285
        },
        {
            "id":134,
            "source":71,
            "target":134,
            "value":0.4538579338390742,
            "lineStyle":{
                "width":0.4538579338390742,
                "opacity":0.5,
                "curveness":0.3
            },
            "symbolSize":4.538579338390742
        },
        {
            "id":135,
            "source":71,
            "target":135,
            "value":0.6588116805416661,
            "lineStyle":{
                "width":0.6588116805416661,
                "opacity":0.5,
                "curveness":0.3
            },
            "symbolSize":6.588116805416661
        },
        {
            "id":136,
            "source":71,
            "target":136,
            "value":0.2955684419936765,
            "lineStyle":{
                "width":0.2955684419936765,
                "opacity":0.5,
                "curveness":0.3
            },
            "symbolSize":2.955684419936765
        },
        {
            "id":137,
            "source":71,
            "target":137,
            "value":0.09562679538882682,
            "lineStyle":{
                "width":0.09562679538882682,
                "opacity":0.5,
                "curveness":0.3
            },
            "symbolSize":0.9562679538882681
        },
        {
            "id":138,
            "source":71,
            "target":138,
            "value":0.30720824073182895,
            "lineStyle":{
                "width":0.30720824073182895,
                "opacity":0.5,
                "curveness":0.3
            },
            "symbolSize":3.0720824073182893
        },
        {
            "id":139,
            "source":71,
            "target":139,
            "value":0.10720689428249275,
            "lineStyle":{
                "width":0.10720689428249275,
                "opacity":0.5,
                "curveness":0.3
            },
            "symbolSize":1.0720689428249275
        },
        {
            "id":140,
            "source":71,
            "target":140,
            "value":0.41888460672996597,
            "lineStyle":{
                "width":0.41888460672996597,
                "opacity":0.5,
                "curveness":0.3
            },
            "symbolSize":4.18884606729966
        },
        {
            "id":141,
            "source":71,
            "target":141,
            "value":0.10844956262972603,
            "lineStyle":{
                "width":0.10844956262972603,
                "opacity":0.5,
                "curveness":0.3
            },
            "symbolSize":1.0844956262972603
        },
        {
            "id":142,
            "source":71,
            "target":142,
            "value":0.37281124659386206,
            "lineStyle":{
                "width":0.37281124659386206,
                "opacity":0.5,
                "curveness":0.3
            },
            "symbolSize":3.7281124659386204
        },
        {
            "id":143,
            "source":71,
            "target":143,
            "value":0.6293445353044647,
            "lineStyle":{
                "width":0.6293445353044647,
                "opacity":0.5,
                "curveness":0.3
            },
            "symbolSize":6.293445353044646
        },
        {
            "id":144,
            "source":71,
            "target":144,
            "value":0.31873620796683516,
            "lineStyle":{
                "width":0.31873620796683516,
                "opacity":0.5,
                "curveness":0.3
            },
            "symbolSize":3.1873620796683517
        },
        {
            "id":145,
            "source":71,
            "target":145,
            "value":0.04035686538117815,
            "lineStyle":{
                "width":0.04035686538117815,
                "opacity":0.5,
                "curveness":0.3
            },
            "symbolSize":0.40356865381178153
        },
        {
            "id":146,
            "source":71,
            "target":146,
            "value":0.47999644002765635,
            "lineStyle":{
                "width":0.47999644002765635,
                "opacity":0.5,
                "curveness":0.3
            },
            "symbolSize":4.799964400276563
        },
        {
            "id":147,
            "source":71,
            "target":147,
            "value":0.27767288114236033,
            "lineStyle":{
                "width":0.27767288114236033,
                "opacity":0.5,
                "curveness":0.3
            },
            "symbolSize":2.7767288114236033
        },
        {
            "id":148,
            "source":71,
            "target":148,
            "value":0.022890864570055784,
            "lineStyle":{
                "width":0.022890864570055784,
                "opacity":0.5,
                "curveness":0.3
            },
            "symbolSize":0.22890864570055786
        },
        {
            "id":149,
            "source":71,
            "target":149,
            "value":0.09820569869085177,
            "lineStyle":{
                "width":0.09820569869085177,
                "opacity":0.5,
                "curveness":0.3
            },
            "symbolSize":0.9820569869085177
        },
        {
            "id":150,
            "source":71,
            "target":150,
            "value":0.2532530452240872,
            "lineStyle":{
                "width":0.2532530452240872,
                "opacity":0.5,
                "curveness":0.3
            },
            "symbolSize":2.532530452240872
        },
        {
            "id":151,
            "source":71,
            "target":151,
            "value":0.15926078336232896,
            "lineStyle":{
                "width":0.15926078336232896,
                "opacity":0.5,
                "curveness":0.3
            },
            "symbolSize":1.5926078336232896
        }
    ]
}